mink/__init__.py
mink/configuration.py
mink/constants.py
mink/contrib/__init__.py
mink/contrib/keyboard_teleop/KEYBOARD.md
mink/contrib/keyboard_teleop/__init__.py
mink/contrib/keyboard_teleop/keycodes.py
mink/contrib/keyboard_teleop/teleop_mocap.py
mink/exceptions.py
mink/lie/__init__.py
mink/lie/base.py
mink/lie/se3.py
mink/lie/so3.py
mink/lie/utils.py
mink/limits/__init__.py
mink/limits/collision_avoidance_limit.py
mink/limits/configuration_limit.py
mink/limits/limit.py
mink/limits/velocity_limit.py
mink/py.typed
mink/solve_ik.py
mink/tasks/__init__.py
mink/tasks/com_task.py
mink/tasks/damping_task.py
mink/tasks/dof_freezing_task.py
mink/tasks/equality_constraint_task.py
mink/tasks/frame_task.py
mink/tasks/kinetic_energy_regularization_task.py
mink/tasks/posture_task.py
mink/tasks/relative_frame_task.py
mink/tasks/task.py
mink/utils.py
mink-1.0.0.dist-info/licenses/LICENSE
mink-1.0.0.dist-info/WHEEL
mink-1.0.0.dist-info/METADATA
mink-1.0.0.dist-info/RECORD
