Metadata-Version: 2.4
Name: mink
Version: 1.0.0
Summary: Python inverse kinematics based on MuJoCo
Keywords: inverse,kinematics,mujoco
Author: Kevin Zakka
Author-email: Kevin Zakka <zakka@berkeley.edu>
License-Expression: Apache-2.0
License-File: LICENSE
Classifier: Development Status :: 5 - Production/Stable
Classifier: Framework :: Robot Framework :: Library
Classifier: Intended Audience :: Developers
Classifier: Intended Audience :: Science/Research
Classifier: License :: OSI Approved :: Apache Software License
Classifier: Programming Language :: Python :: 3.10
Classifier: Programming Language :: Python :: 3.11
Classifier: Programming Language :: Python :: 3.12
Classifier: Programming Language :: Python :: 3.13
Classifier: Topic :: Scientific/Engineering
Requires-Dist: mujoco>=3.3.6
Requires-Dist: qpsolvers[daqp]>=4.3.1
Requires-Dist: typing-extensions
Requires-Python: >=3.10, <3.14
Project-URL: Changelog, https://github.com/kevinzakka/mink/blob/main/CHANGELOG.md
Project-URL: Documentation, https://kevinzakka.github.io/mink/
Project-URL: Homepage, https://kevinzakka.github.io/mink/
Project-URL: Source, https://github.com/kevinzakka/mink
Project-URL: Tracker, https://github.com/kevinzakka/mink/issues
